cfdp/__init__.py
cfdp/constants.py
cfdp/core.py
cfdp/event.py
cfdp/transaction.py
cfdp/filestore/__init__.py
cfdp/filestore/base.py
cfdp/filestore/native.py
cfdp/machines/__init__.py
cfdp/machines/base.py
cfdp/machines/receiver1.py
cfdp/machines/receiver2.py
cfdp/machines/sender1.py
cfdp/machines/sender2.py
cfdp/machines/timer.py
cfdp/meta/__init__.py
cfdp/meta/datafield.py
cfdp/meta/filestore.py
cfdp/meta/message.py
cfdp/pdu/__init__.py
cfdp/pdu/ack.py
cfdp/pdu/eof.py
cfdp/pdu/filedata.py
cfdp/pdu/finished.py
cfdp/pdu/header.py
cfdp/pdu/keep_alive.py
cfdp/pdu/metadata.py
cfdp/pdu/nak.py
cfdp/pdu/prompt.py
cfdp/transport/__init__.py
cfdp/transport/base.py
cfdp/transport/spacepacket.py
cfdp/transport/udp.py
cfdp/transport/zmq.py
cfdp-2.1.0.dist-info/LICENSE.txt
cfdp-2.1.0.dist-info/METADATA
cfdp-2.1.0.dist-info/WHEEL
cfdp-2.1.0.dist-info/top_level.txt
cfdp-2.1.0.dist-info/RECORD
