Metadata-Version: 2.1
Name: cfdp
Version: 2.1.0
Summary: CCSDS File Delivery Protocol
Author-email: LibreCube <info@librecube.org>
License: MIT
License-File: LICENSE.txt
